regex_log_parser/__init__.py
regex_log_parser/processor.py
regex_log_parser/handlers/__init__.py
regex_log_parser/handlers/base.py
regex_log_parser/handlers/postgres.py
regex_log_parser-1.0.0.dist-info/LICENSE
regex_log_parser-1.0.0.dist-info/METADATA
regex_log_parser-1.0.0.dist-info/WHEEL
regex_log_parser-1.0.0.dist-info/top_level.txt
regex_log_parser-1.0.0.dist-info/RECORD
