Metadata-Version: 2.1
Name: regex-log-parser
Version: 1.0.0
Summary: Python library to process hetrogenous log files by defining simple regex patterns and functions to handle them. Includes classes to parse data into postgres database.
Author-email: Harrison Barlow <harrison.barlow@curtin.edu>
License: Mozilla Public License Version 2.0
Project-URL: Homepage, https://github.com/MWATelescope/log_processing/
Keywords: regex,log,parsing
Classifier: License :: OSI Approved :: MIT License
Classifier: Programming Language :: Python
Classifier: Programming Language :: Python :: 3
Requires-Python: >=3.10
License-File: LICENSE
Provides-Extra: dev
Requires-Dist: pip-tools ; extra == 'dev'
Requires-Dist: pytest ; extra == 'dev'
Requires-Dist: pytest-postgresql ; extra == 'dev'
Requires-Dist: coverage ; extra == 'dev'
Provides-Extra: postgres
Requires-Dist: psycopg (>=3.0) ; extra == 'postgres'
